azure/cognitiveservices/search/autosuggest/__init__.py
azure/cognitiveservices/search/autosuggest/_auto_suggest_client.py
azure/cognitiveservices/search/autosuggest/_configuration.py
azure/cognitiveservices/search/autosuggest/py.typed
azure/cognitiveservices/search/autosuggest/version.py
azure/cognitiveservices/search/autosuggest/models/__init__.py
azure/cognitiveservices/search/autosuggest/models/_auto_suggest_client_enums.py
azure/cognitiveservices/search/autosuggest/models/_models.py
azure/cognitiveservices/search/autosuggest/models/_models_py3.py
azure/cognitiveservices/search/autosuggest/operations/__init__.py
azure/cognitiveservices/search/autosuggest/operations/_auto_suggest_client_operations.py
azure_cognitiveservices_search_autosuggest-0.2.1.dist-info/LICENSE
azure_cognitiveservices_search_autosuggest-0.2.1.dist-info/METADATA
azure_cognitiveservices_search_autosuggest-0.2.1.dist-info/WHEEL
azure_cognitiveservices_search_autosuggest-0.2.1.dist-info/top_level.txt
azure_cognitiveservices_search_autosuggest-0.2.1.dist-info/RECORD
